{
  "id": "5e78efd1-70eb-4285-b478-7afc29502b66",
  "prevId": "34a40684-fdc8-445c-b011-21aea0b602a7",
  "version": "5",
  "dialect": "pg",
  "tables": {
    "accounts": {
      "name": "accounts",
      "schema": "",
      "columns": {
        "id": {
          "name": "id",
          "type": "serial",
          "primaryKey": true,
          "notNull": true
        },
        "name": {
          "name": "name",
          "type": "text",
          "primaryKey": false,
          "notNull": true
        },
        "email": {
          "name": "email",
          "type": "text",
          "primaryKey": false,
          "notNull": true
        },
        "password": {
          "name": "password",
          "type": "text",
          "primaryKey": false,
          "notNull": true
        },
        "created_at": {
          "name": "created_at",
          "type": "timestamp",
          "primaryKey": false,
          "notNull": true,
          "default": "now()"
        }
      },
      "indexes": {},
      "foreignKeys": {},
      "compositePrimaryKeys": {},
      "uniqueConstraints": {}
    },
    "accounts_to_roles": {
      "name": "accounts_to_roles",
      "schema": "",
      "columns": {
        "account_id": {
          "name": "account_id",
          "type": "integer",
          "primaryKey": false,
          "notNull": true
        },
        "role_id": {
          "name": "role_id",
          "type": "integer",
          "primaryKey": false,
          "notNull": true
        }
      },
      "indexes": {},
      "foreignKeys": {
        "accounts_to_roles_account_id_accounts_id_fk": {
          "name": "accounts_to_roles_account_id_accounts_id_fk",
          "tableFrom": "accounts_to_roles",
          "tableTo": "accounts",
          "columnsFrom": [
            "account_id"
          ],
          "columnsTo": [
            "id"
          ],
          "onDelete": "no action",
          "onUpdate": "no action"
        },
        "accounts_to_roles_role_id_roles_id_fk": {
          "name": "accounts_to_roles_role_id_roles_id_fk",
          "tableFrom": "accounts_to_roles",
          "tableTo": "roles",
          "columnsFrom": [
            "role_id"
          ],
          "columnsTo": [
            "id"
          ],
          "onDelete": "no action",
          "onUpdate": "no action"
        }
      },
      "compositePrimaryKeys": {
        "accounts_to_roles_account_id_role_id_pk": {
          "name": "accounts_to_roles_account_id_role_id_pk",
          "columns": [
            "account_id",
            "role_id"
          ]
        }
      },
      "uniqueConstraints": {}
    },
    "activities": {
      "name": "activities",
      "schema": "",
      "columns": {
        "id": {
          "name": "id",
          "type": "serial",
          "primaryKey": true,
          "notNull": true
        },
        "name": {
          "name": "name",
          "type": "text",
          "primaryKey": false,
          "notNull": true
        },
        "start_at": {
          "name": "start_at",
          "type": "timestamp",
          "primaryKey": false,
          "notNull": false
        },
        "end_at": {
          "name": "end_at",
          "type": "timestamp",
          "primaryKey": false,
          "notNull": false
        },
        "quota": {
          "name": "quota",
          "type": "integer",
          "primaryKey": false,
          "notNull": false
        },
        "price": {
          "name": "price",
          "type": "numeric",
          "primaryKey": false,
          "notNull": false
        },
        "created_at": {
          "name": "created_at",
          "type": "timestamp",
          "primaryKey": false,
          "notNull": true,
          "default": "now()"
        }
      },
      "indexes": {},
      "foreignKeys": {},
      "compositePrimaryKeys": {},
      "uniqueConstraints": {}
    },
    "admins": {
      "name": "admins",
      "schema": "",
      "columns": {
        "id": {
          "name": "id",
          "type": "serial",
          "primaryKey": true,
          "notNull": true
        },
        "account_id": {
          "name": "account_id",
          "type": "integer",
          "primaryKey": false,
          "notNull": false
        },
        "name": {
          "name": "name",
          "type": "text",
          "primaryKey": false,
          "notNull": true
        },
        "icon": {
          "name": "icon",
          "type": "text",
          "primaryKey": false,
          "notNull": false,
          "default": "'default_admin.png'"
        },
        "created_at": {
          "name": "created_at",
          "type": "timestamp",
          "primaryKey": false,
          "notNull": true,
          "default": "now()"
        }
      },
      "indexes": {},
      "foreignKeys": {
        "admins_account_id_accounts_id_fk": {
          "name": "admins_account_id_accounts_id_fk",
          "tableFrom": "admins",
          "tableTo": "accounts",
          "columnsFrom": [
            "account_id"
          ],
          "columnsTo": [
            "id"
          ],
          "onDelete": "no action",
          "onUpdate": "no action"
        }
      },
      "compositePrimaryKeys": {},
      "uniqueConstraints": {}
    },
    "friends": {
      "name": "friends",
      "schema": "",
      "columns": {
        "user_1_id": {
          "name": "user_1_id",
          "type": "integer",
          "primaryKey": false,
          "notNull": false
        },
        "user_2_id": {
          "name": "user_2_id",
          "type": "integer",
          "primaryKey": false,
          "notNull": false
        }
      },
      "indexes": {},
      "foreignKeys": {
        "friends_user_1_id_users_id_fk": {
          "name": "friends_user_1_id_users_id_fk",
          "tableFrom": "friends",
          "tableTo": "users",
          "columnsFrom": [
            "user_1_id"
          ],
          "columnsTo": [
            "id"
          ],
          "onDelete": "no action",
          "onUpdate": "no action"
        },
        "friends_user_2_id_users_id_fk": {
          "name": "friends_user_2_id_users_id_fk",
          "tableFrom": "friends",
          "tableTo": "users",
          "columnsFrom": [
            "user_2_id"
          ],
          "columnsTo": [
            "id"
          ],
          "onDelete": "no action",
          "onUpdate": "no action"
        }
      },
      "compositePrimaryKeys": {
        "friends_user_1_id_user_2_id_pk": {
          "name": "friends_user_1_id_user_2_id_pk",
          "columns": [
            "user_1_id",
            "user_2_id"
          ]
        }
      },
      "uniqueConstraints": {}
    },
    "genderOptions": {
      "name": "genderOptions",
      "schema": "",
      "columns": {
        "id": {
          "name": "id",
          "type": "serial",
          "primaryKey": true,
          "notNull": true
        },
        "name": {
          "name": "name",
          "type": "text",
          "primaryKey": false,
          "notNull": true
        }
      },
      "indexes": {},
      "foreignKeys": {},
      "compositePrimaryKeys": {},
      "uniqueConstraints": {}
    },
    "roles": {
      "name": "roles",
      "schema": "",
      "columns": {
        "id": {
          "name": "id",
          "type": "serial",
          "primaryKey": true,
          "notNull": true
        },
        "name": {
          "name": "name",
          "type": "text",
          "primaryKey": false,
          "notNull": true
        },
        "description": {
          "name": "description",
          "type": "text",
          "primaryKey": false,
          "notNull": false
        }
      },
      "indexes": {},
      "foreignKeys": {},
      "compositePrimaryKeys": {},
      "uniqueConstraints": {}
    },
    "users": {
      "name": "users",
      "schema": "",
      "columns": {
        "id": {
          "name": "id",
          "type": "serial",
          "primaryKey": true,
          "notNull": true
        },
        "account_id": {
          "name": "account_id",
          "type": "integer",
          "primaryKey": false,
          "notNull": false
        },
        "gender_option_id": {
          "name": "gender_option_id",
          "type": "integer",
          "primaryKey": false,
          "notNull": false
        },
        "name": {
          "name": "name",
          "type": "text",
          "primaryKey": false,
          "notNull": true
        },
        "icon": {
          "name": "icon",
          "type": "text",
          "primaryKey": false,
          "notNull": false,
          "default": "'default_user.png'"
        },
        "firstname": {
          "name": "firstname",
          "type": "text",
          "primaryKey": false,
          "notNull": true
        },
        "lastname": {
          "name": "lastname",
          "type": "text",
          "primaryKey": false,
          "notNull": true
        },
        "phone": {
          "name": "phone",
          "type": "text",
          "primaryKey": false,
          "notNull": false
        },
        "weight": {
          "name": "weight",
          "type": "numeric",
          "primaryKey": false,
          "notNull": false
        },
        "birth": {
          "name": "birth",
          "type": "date",
          "primaryKey": false,
          "notNull": false
        },
        "calories": {
          "name": "calories",
          "type": "integer",
          "primaryKey": false,
          "notNull": false
        },
        "scores": {
          "name": "scores",
          "type": "integer",
          "primaryKey": false,
          "notNull": false
        },
        "created_at": {
          "name": "created_at",
          "type": "timestamp",
          "primaryKey": false,
          "notNull": true,
          "default": "now()"
        }
      },
      "indexes": {},
      "foreignKeys": {
        "users_account_id_accounts_id_fk": {
          "name": "users_account_id_accounts_id_fk",
          "tableFrom": "users",
          "tableTo": "accounts",
          "columnsFrom": [
            "account_id"
          ],
          "columnsTo": [
            "id"
          ],
          "onDelete": "no action",
          "onUpdate": "no action"
        },
        "users_gender_option_id_genderOptions_id_fk": {
          "name": "users_gender_option_id_genderOptions_id_fk",
          "tableFrom": "users",
          "tableTo": "genderOptions",
          "columnsFrom": [
            "gender_option_id"
          ],
          "columnsTo": [
            "id"
          ],
          "onDelete": "no action",
          "onUpdate": "no action"
        }
      },
      "compositePrimaryKeys": {},
      "uniqueConstraints": {}
    },
    "users_to_activities": {
      "name": "users_to_activities",
      "schema": "",
      "columns": {
        "user_id": {
          "name": "user_id",
          "type": "integer",
          "primaryKey": false,
          "notNull": true
        },
        "activity_id": {
          "name": "activity_id",
          "type": "integer",
          "primaryKey": false,
          "notNull": true
        }
      },
      "indexes": {},
      "foreignKeys": {
        "users_to_activities_user_id_users_id_fk": {
          "name": "users_to_activities_user_id_users_id_fk",
          "tableFrom": "users_to_activities",
          "tableTo": "users",
          "columnsFrom": [
            "user_id"
          ],
          "columnsTo": [
            "id"
          ],
          "onDelete": "no action",
          "onUpdate": "no action"
        },
        "users_to_activities_activity_id_activities_id_fk": {
          "name": "users_to_activities_activity_id_activities_id_fk",
          "tableFrom": "users_to_activities",
          "tableTo": "activities",
          "columnsFrom": [
            "activity_id"
          ],
          "columnsTo": [
            "id"
          ],
          "onDelete": "no action",
          "onUpdate": "no action"
        }
      },
      "compositePrimaryKeys": {
        "users_to_activities_user_id_activity_id_pk": {
          "name": "users_to_activities_user_id_activity_id_pk",
          "columns": [
            "user_id",
            "activity_id"
          ]
        }
      },
      "uniqueConstraints": {}
    }
  },
  "enums": {},
  "schemas": {},
  "_meta": {
    "columns": {},
    "schemas": {},
    "tables": {}
  }
}